flaskbb_plugin_private_memberlist-1.2.dist-info/DESCRIPTION.rst
flaskbb_plugin_private_memberlist-1.2.dist-info/METADATA
flaskbb_plugin_private_memberlist-1.2.dist-info/RECORD
flaskbb_plugin_private_memberlist-1.2.dist-info/WHEEL
flaskbb_plugin_private_memberlist-1.2.dist-info/entry_points.txt
flaskbb_plugin_private_memberlist-1.2.dist-info/metadata.json
flaskbb_plugin_private_memberlist-1.2.dist-info/top_level.txt
memberlist/__init__.py
