Metadata-Version: 2.0
Name: flaskbb-plugin-private-memberlist
Version: 1.2
Summary: Require login to view the member list
Home-page: https://github.com/haliphax/flaskbb-plugin-private-memberlist
Author: haliphax
Author-email: haliphax@github.com
License: UNKNOWN
Platform: any
Classifier: Environment :: Web Environment
Classifier: Environment :: Plugins
Classifier: Framework :: Flask
Classifier: Intended Audience :: Developers
Classifier: License :: OSI Approved :: MIT License
Classifier: Operating System :: OS Independent
Classifier: Programming Language :: Python
Classifier: Programming Language :: Python :: 2.7
Classifier: Topic :: Internet :: WWW/HTTP :: Dynamic Content
Classifier: Topic :: Software Development :: Libraries :: Python Modules
